utilblob/__init__.py
utilblob/_core.py
utilblob/chars.py
utilblob/cli/__init__.py
utilblob/cli/_base.py
utilblob/cli/arg_parsing.py
utilblob/context.py
utilblob/csv_utils.py
utilblob/debugging_utils.py
utilblob/enum_utils.py
utilblob/err.py
utilblob/factories.py
utilblob/fs.py
utilblob/func_utils.py
utilblob/import_utils.py
utilblob/io_utils.py
utilblob/iter_utils.py
utilblob/more_collections.py
utilblob/numeric_utils.py
utilblob/ops.py
utilblob/profiling.py
utilblob/recipes/collections.py
utilblob/recipes/singleton.py
utilblob/regex_recipes.py
utilblob/rich_utils.py
utilblob/text.py
utilblob/time_utils.py
utilblob/tree.py
utilblob/type_utils.py
utilblob/with_progress.py
utilblob_py-0.1.0.dist-info/METADATA
utilblob_py-0.1.0.dist-info/WHEEL
utilblob_py-0.1.0.dist-info/RECORD
